exeplot/VERSION.txt
exeplot/__conf__.py
exeplot/__info__.py
exeplot/__init__.py
exeplot/__main__.py
exeplot/utils.py
exeplot/plots/__common__.py
exeplot/plots/__init__.py
exeplot/plots/byte.py
exeplot/plots/diff.py
exeplot/plots/entropy.py
exeplot/plots/graph.py
exeplot/plots/nested_pie.py
exeplot/plots/pie.py
exeplot-0.4.3.dist-info/licenses/LICENSE
exeplot-0.4.3.dist-info/METADATA
exeplot-0.4.3.dist-info/WHEEL
exeplot-0.4.3.dist-info/entry_points.txt
exeplot-0.4.3.dist-info/top_level.txt
exeplot-0.4.3.dist-info/RECORD
