Metadata-Version: 2.4
Name: exeplot
Version: 0.4.3
Summary: Library for plotting executable samples supporting multiple formats
Author-email: Alexandre D'Hondt <alexandre.dhondt@gmail.com>
License:                     GNU GENERAL PUBLIC LICENSE
Project-URL: documentation, https://python-exeplot.readthedocs.io/en/latest/?badge=latest
Project-URL: homepage, https://github.com/packing-box/python-exeplot
Project-URL: issues, https://github.com/packing-box/python-exeplot/issues
Project-URL: repository, https://github.com/packing-box/python-exeplot
Keywords: python,development,programming,executable-samples,plot,entropy,cfg
Classifier: Development Status :: 5 - Production/Stable
Classifier: Environment :: Console
Classifier: Intended Audience :: Developers
Classifier: License :: OSI Approved :: GNU General Public License v3 or later (GPLv3+)
Classifier: Programming Language :: Python :: 3
Classifier: Topic :: Software Development :: Libraries :: Python Modules
Requires-Python: <4,>=3.9
License-File: LICENSE
Requires-Dist: lief>=0.16.1
Requires-Dist: matplotlib
Provides-Extra: graph
Requires-Dist: angr>=9.2; extra == "graph"
Requires-Dist: networkx>=3.4.2; extra == "graph"
Requires-Dist: numpy; extra == "graph"
Requires-Dist: pygraphviz>=1.14; extra == "graph"
Requires-Dist: unicorn>2; extra == "graph"
Dynamic: license-file
